{
  "architecture": "resnet56",
  "dataset": "cifar100",
  "method": "FPGM",
  "mode": "oneshot",
  "target_ratio": 0.7,
  "seed": 456,
  "epochs": 30,
  "baseline_acc": 72.56,
  "pruned_acc": 1.76,
  "final_acc": 65.84,
  "macro_f1": 65.81381844922282,
  "balanced_acc": 65.84,
  "worst_class_acc": 34.0,
  "worst10_mean_acc": 42.3,
  "collapse_class_count_5pct": 0,
  "collapse_class_count_10pct": 0,
  "params_before": 861620,
  "params_after": 267224,
  "param_reduction_pct": 68.98586383788677,
  "compression_ratio": 3.224336137472682,
  "score_time_s": 0.07353067398071289,
  "total_time_s": 288.7,
  "score_meta": {
    "version": "FPGM",
    "method": "FPGM",
    "fpgm_metric": "l2",
    "score_time_s": 0.07353067398071289
  },
  "method_version": "FPGM",
  "gate_on_rate": 0.0,
  "semantic_applied_rate": 0.0,
  "total_swaps": 0,
  "avg_swaps_per_layer": 0.0,
  "tau_candidate": 0.0,
  "tau_dyn": 0.0,
  "quality_mean": 0.0,
  "anchor_weights": {},
  "boundary_quantiles": [],
  "risk_guard_rate": 0.0,
  "risk_protect_ratio": 0.0,
  "risk_tol": 0.0,
  "hard_class_count": 0,
  "hard_class_ids": [],
  "hard_class_mean_acc": 0.0,
  "lambda_severity": 0.0,
  "protected_channels_total": 0,
  "protected_channels_ratio": 0.0,
  "protected_channels_ratio_per_layer": {},
  "budget_mode": "",
  "iso_flops_target": null,
  "iso_flops_actual": null,
  "iso_flops_ratio": null,
  "timestamp": "2026-03-01T13:38:06.143429"
}