{
  "architecture": "vgg16",
  "dataset": "cifar100",
  "method": "GRA-CHIP-v4C-noProtect",
  "mode": "oneshot",
  "target_ratio": 0.9,
  "seed": 42,
  "epochs": 30,
  "baseline_acc": 73.58,
  "pruned_acc": 1.0,
  "final_acc": 42.98,
  "macro_f1": 42.321607435032696,
  "balanced_acc": 42.98,
  "worst_class_acc": 8.0,
  "worst10_mean_acc": 14.1,
  "collapse_class_count_5pct": 0,
  "collapse_class_count_10pct": 2,
  "params_before": 14774436,
  "params_after": 153364,
  "param_reduction_pct": 98.96196375956416,
  "compression_ratio": 96.3357502412561,
  "score_time_s": 51.70355033874512,
  "total_time_s": 278.8,
  "score_meta": {
    "version": "GRA-CHIP-v4C",
    "method": "GRA-CHIP-v4C",
    "anchor_weights": {
      "chip": 0.6,
      "taylor": 0.25,
      "fisher": 0.15
    },
    "n_layers": 13,
    "score_time_s": 51.70355033874512,
    "enable_protection": false,
    "adaptive_lambda": true,
    "budget_mode": "none",
    "hard_class_count": 0,
    "hard_class_ids": [],
    "hard_class_mean_acc": 0.0,
    "severity": 0.0,
    "lambda_severity": 1.0,
    "protected_channels_ratio_per_layer": {}
  },
  "method_version": "GRA-CHIP-v4C",
  "gate_on_rate": 0.0,
  "semantic_applied_rate": 0.0,
  "total_swaps": 0,
  "avg_swaps_per_layer": 0.0,
  "tau_candidate": 0.0,
  "tau_dyn": 0.0,
  "quality_mean": 0.0,
  "anchor_weights": {
    "chip": 0.6,
    "taylor": 0.25,
    "fisher": 0.15
  },
  "boundary_quantiles": [],
  "risk_guard_rate": 0.0,
  "risk_protect_ratio": 0.0,
  "risk_tol": 0.0,
  "hard_class_count": 0,
  "hard_class_ids": [],
  "hard_class_mean_acc": 0.0,
  "lambda_severity": 1.0,
  "protected_channels_total": 0,
  "protected_channels_ratio": 0.0,
  "protected_channels_ratio_per_layer": {},
  "budget_mode": "none",
  "iso_flops_target": null,
  "iso_flops_actual": null,
  "iso_flops_ratio": null,
  "timestamp": "2026-02-26T05:33:09.924226"
}